RAGToolBox/Download_punkt.sh
RAGToolBox/__init__.py
RAGToolBox/augmenter.py
RAGToolBox/chunk.py
RAGToolBox/config/prompts.yaml
RAGToolBox/embeddings.py
RAGToolBox/index.py
RAGToolBox/loader.py
RAGToolBox/logging.py
RAGToolBox/retriever.py
RAGToolBox/types.py
RAGToolBox/vector_store.py
ragtoolbox-0.1.0.dist-info/LICENSE
ragtoolbox-0.1.0.dist-info/METADATA
ragtoolbox-0.1.0.dist-info/WHEEL
ragtoolbox-0.1.0.dist-info/RECORD
