Metadata-Version: 2.3
Name: ragtoolbox
Version: 0.1.0
Summary: Modular toolkit for building Retrieval-Augmented Generation (RAG) pipelines.
License: MIT
Author: Nick-Nunley
Author-email: nicknunley17@ucla.edu
Requires-Python: >=3.10,<4.0
Classifier: License :: OSI Approved :: MIT License
Classifier: Programming Language :: Python :: 3
Classifier: Programming Language :: Python :: 3.10
Classifier: Programming Language :: Python :: 3.11
Classifier: Programming Language :: Python :: 3.12
Classifier: Programming Language :: Python :: 3.13
Provides-Extra: chromadb
Provides-Extra: ncbi
Provides-Extra: openai
Provides-Extra: transformers
Requires-Dist: beautifulsoup4 (>=4.12.0,<5.0.0)
Requires-Dist: biopython (>=1.8.0) ; extra == "ncbi"
Requires-Dist: chromadb (>=1.0.15) ; extra == "chromadb"
Requires-Dist: fastembed (>=0.7.1,<0.8.0)
Requires-Dist: html2text (>=2025.4.15,<2026.0.0)
Requires-Dist: huggingface_hub (>=0.33.5,<0.34.0)
Requires-Dist: nltk (>=3.9.1,<4.0.0)
Requires-Dist: numpy (>=1.26,<2.3) ; python_version < "3.11"
Requires-Dist: numpy (>=2.3,<3.0) ; python_version >= "3.11"
Requires-Dist: openai (>=1.95.1) ; extra == "openai"
Requires-Dist: pdfplumber (>=0.11.7,<0.12.0)
Requires-Dist: pyyaml (>=6.0.2,<7.0.0)
Requires-Dist: readability-lxml (>=0.8.4.1,<0.9.0.0)
Requires-Dist: requests (>=2.32.4,<3.0.0)
Requires-Dist: torch (>=2.7.1,<3.0.0) ; extra == "transformers"
Requires-Dist: transformers (>=4.30.0,<5.0.0) ; extra == "transformers"
